general_intelligence-0.7.0.dist-info/licenses/LICENSE
gi/__init__.py
gi/core.py
gi/knowledge/__init__.py
gi/knowledge/functions.py
general_intelligence-0.7.0.dist-info/METADATA
general_intelligence-0.7.0.dist-info/WHEEL
general_intelligence-0.7.0.dist-info/top_level.txt
general_intelligence-0.7.0.dist-info/RECORD
