Metadata-Version: 2.4
Name: general_intelligence
Version: 0.7.0
Summary: Self-organizing knowledge systems for structural pattern learning
Author-email: Oluwaseyi Shoboyejo <sunmark130@gmail.com>
License-Expression: MIT
Project-URL: Homepage, https://github.com/mksunny1/general-intelligence
Project-URL: Issues, https://github.com/mksunny1/general-intelligence/issues
Classifier: Development Status :: 3 - Alpha
Classifier: Intended Audience :: Science/Research
Classifier: Programming Language :: Python :: 3
Classifier: Operating System :: OS Independent
Requires-Python: >=3.9
License-File: LICENSE
Dynamic: license-file
